idem_spotinst/conf.py
idem_spotinst/version.py
idem_spotinst/acct/spotinst/init.py
idem_spotinst/exec/spotinst/init.py
idem_spotinst/states/spotinst/ocean/aws/k8s_cluster.py
idem_spotinst/states/spotinst/ocean/aws/launch_spec.py
idem_spotinst/tool/spotinst/comment_utils.py
idem_spotinst/tool/spotinst/state_comparison_utils.py
idem_spotinst/tool/spotinst/state_utils.py
idem_spotinst/tool/spotinst/ocean/aws/conversion_utils.py
idem_spotinst/tool/spotinst/ocean/aws/k8s_cluster_utils.py
idem_spotinst/tool/spotinst/ocean/aws/tag_utils.py
idem_spotinst-2.0.0.dist-info/LICENSE
idem_spotinst-2.0.0.dist-info/METADATA
idem_spotinst-2.0.0.dist-info/WHEEL
idem_spotinst-2.0.0.dist-info/entry_points.txt
idem_spotinst-2.0.0.dist-info/top_level.txt
idem_spotinst-2.0.0.dist-info/RECORD
